{
	"_id": "5f975e93c8e2fa17a0708990",
	"Confs": {
		"urlBase": "http://localhost:3001/Sistema",
		"active": "true",
		"datetime": "1603755667592"
	},
	"MenuBar": {
		"id": "MainMenuBar",
		"descrição": "Sistema de Gerenciamento de Plantões",
		"maxItensPerLine": 7,
		"Hierarquia": {			
			"Administração da Escala": {
				"VaraPlantonistaCRUD":null,
				"EscalaPlantaoCRUD":null,
				"JuizCRUD":null,
				"AfastamentoCRUD":null				
			},
			"Parâmetros do Sistema": {				
				"FeriadoCRUD":null,
				"TipoPlantaoCRUD":null,
				"TipoAfastamentoCRUD":null,
				"RelatorioCRUD":null,
				"ParametroJsonCRUD":null,
				"ModeloTextoCRUD":null,
				"GeradorTextosWA":null
			}
		}
	},
	"webapiDialogs":[
		{
			"id":"GeradorTextosWA",
			"nome":"Gerador de Textos",
			"tipo":"webapiDialog",
			"desligaUrlBase":"true",
			"urlApi":"https://localhost:3000/gerar_texto_modelo",
			"httpMethod": "POST",
			"bindingStrategy": "JsonInJsonOut",
			"bindingParameters": {},
			"nomeBotao": "Gerador de Textos",
			"in":{
				"camposFormObjeto": ["#modelo", "#parametros"],
				"labelsFormObjeto": ["Modelo", "Parâmetros"],
				"readOnlyFormObjeto": ["", ""],
				"inputFieldFormObjeto": ["<input type=\"text\"","<textarea "],
				"camposObjeto": ["modelo", "parametros"],
				"campoObjetoId": null,
				"camposFormClassObjeto": ["form-control","form-control"],
				"tipoCamposObjeto": ["text","text"],
				"chooseFormObjeto": ["",""],
				"accordions": null,
				"camposFormObjetoOrder":["1","2"]
			},
			"out":{
				"camposFormObjeto": ["#texto"],
				"labelsFormObjeto": ["Texto"],
				"readOnlyFormObjeto": ["readOnly"],
				"inputFieldFormObjeto": ["<textarea "],
				"camposObjeto": ["texto"],			
				"camposFormClassObjeto": ["form-control"],
				"tipoCamposObjeto": ["tinymce"],
				"chooseFormObjeto": [""],
				"accordions": null,
				"camposFormObjetoOrder": ["1"],
				"camposListagemObjeto":["texto"],
				"campoObjetoId": null
			}
		}
	],
	"entities":[
		{
			"id": "CidadeCRUD",
			"tipo": "entity",
			"desligaUrlBase":"true",
			"urlObter": "https://localhost:3000/Obter/?Tipo_Id=cidade_",
			"urlApagar": "https://localhost:3000/Apagar?Tipo_Id=cidade_",
			"urlLoadObjetos": "https://localhost:3000/Listar?qualEntidade=cidade&pageSize=",
			"urlCount": "https://localhost:3000/CountEntity?qualEntidade=cidade",
			"urlIncluir": "https://localhost:3000/Incluir",
			"urlAlterar": "https://localhost:3000/Alterar",
			"nomeEntidade": "cidade",
			"nome": "Cidades",
			"camposFormObjeto": ["#codigo_estado","#codigo", "#nome"],
			"labelsFormObjeto": ["Estado","Código", "Nome"],
			"readOnlyFormObjeto": ["readOnly","readOnly", ""],
			"inputFieldFormObjeto": ["<input type=\"text\"","<input type=\"text\"", "<input type=\"text\""],
			"campoObjetoId": "codigo",
			"camposObjeto": ["codigo_estado","codigo", "nome"],
			"camposListagemObjeto": ["nome"],
			"camposFormObjetoOrder": ["1", "2","3"],
			"camposFormClassObjeto": ["form-control", "form-control", "form-control"],
			"tipoCamposObjeto": ["objectid", "text","objectid"],
			"chooseFormObjeto": ["EstadoCRUD", "",""],
			"IdToViewObjeto": ["EstadoCRUD", "",""]
		},
		{
			"id": "EstadoCRUD",
			"tipo": "entity",
			"desligaUrlBase":"true",
			"urlObter": "https://localhost:3000/Obter/?Tipo_Id=estado_",
			"urlApagar": "https://localhost:3000/Apagar?Tipo_Id=estado_",
			"urlLoadObjetos": "https://localhost:3000/Listar?qualEntidade=estado&pageSize=",
			"urlCount": "https://localhost:3000/CountEntity?qualEntidade=estado",
			"urlIncluir": "https://localhost:3000/Incluir",
			"urlAlterar": "https://localhost:3000/Alterar",
			"nomeEntidade": "estado",
			"nome": "Estados",
			"camposFormObjeto": ["#codigo", "#nome"],
			"labelsFormObjeto": ["Código", "Nome"],
			"readOnlyFormObjeto": ["readOnly", ""],
			"inputFieldFormObjeto": ["<input type=\"text\"", "<input type=\"text\""],
			"campoObjetoId": "codigo",
			"camposObjeto": ["codigo", "nome"],
			"camposListagemObjeto": ["nome"],
			"camposFormObjetoOrder": ["1", "2"],
			"camposFormClassObjeto": ["form-control", "form-control"],
			"tipoCamposObjeto": ["objectid", "text"],
			"chooseFormObjeto": ["", ""]
		},
		{
			"id": "FeriadoCRUD",
			"tipo": "entity",
			"desligaUrlBase":"true",
			"urlObter": "https://localhost:3000/Obter/?Tipo_Id=feriado_",
			"urlApagar": "https://localhost:3000/Apagar?Tipo_Id=feriado_",
			"urlLoadObjetos": "https://localhost:3000/Listar?qualEntidade=feriado&pageSize=",
			"urlCount": "https://localhost:3000/CountEntity?qualEntidade=feriado",
			"urlIncluir": "https://localhost:3000/Incluir",
			"urlAlterar": "https://localhost:3000/Alterar",
			"nomeEntidade": "feriado",
			"nome": "Feriados",
			"camposFormObjeto": ["#codigo_estado","#codigo_cidade","#codigo","#nome","#inicio","#fim"],
			"labelsFormObjeto": ["Estado","Cidade","Código","Nome do Feriado","Início","Fim"],
			"readOnlyFormObjeto": ["readOnly","readOnly", "readOnly","","",""],
			"inputFieldFormObjeto": ["<input type=\"text\"","<input type=\"text\"", "<input type=\"text\""
										,"<input type=\"text\"","<input type=\"text\"","<input type=\"text\""
								],
			"campoObjetoId": "codigo",
			"camposObjeto": ["codigo_estado","codigo_cidade","codigo","nome","inicio","fim"],
			"camposListagemObjeto": ["nome","codigo_cidade","codigo_estado"],
			"camposFormObjetoOrder": ["1", "2","3","4","5","6"],
			"camposFormClassObjeto": ["form-control", "form-control", "form-control", "form-control",
										 "form-control", "form-control"],
			"tipoCamposObjeto": ["objectid", "objectid","objectid","text","date","date"],
			"chooseFormObjeto": ["EstadoCRUD", "CidadeCRUD","","","",""],
			"IdToViewObjeto": ["EstadoCRUD", "CidadeCRUD","","","",""]
		},
		{
			"id": "TipoPlantaoCRUD",
			"tipo": "entity",
			"desligaUrlBase":"true",
			"urlObter": "https://localhost:3000/Obter/?Tipo_Id=tipo_plantao_",
			"urlApagar": "https://localhost:3000/Apagar?Tipo_Id=tipo_plantao_",
			"urlLoadObjetos": "https://localhost:3000/Listar?qualEntidade=tipo_plantao&pageSize=",
			"urlCount": "https://localhost:3000/CountEntity?qualEntidade=tipo_plantao",
			"urlIncluir": "https://localhost:3000/Incluir",
			"urlAlterar": "https://localhost:3000/Alterar",
			"nomeEntidade": "tipo_plantao",
			"nome": "Tipos de Plantão",
			"camposFormObjeto": ["#codigo", "#nome","#descricao"],
			"labelsFormObjeto": ["Código", "Nome","Descrição"],
			"readOnlyFormObjeto": ["readOnly", "",""],
			"inputFieldFormObjeto": ["<input type=\"text\"", "<input type=\"text\"", "<textarea "],
			"campoObjetoId": "codigo",
			"camposObjeto": ["codigo", "nome","descricao"],
			"camposListagemObjeto": ["nome"],
			"camposFormObjetoOrder": ["1", "2","3"],
			"camposFormClassObjeto": ["form-control", "form-control", "form-control"],
			"tipoCamposObjeto": ["objectid", "text","text"],
			"chooseFormObjeto": ["", "",""]
			
		},
		{
			"id": "TipoAfastamentoCRUD",
			"tipo": "entity",
			"desligaUrlBase":"true",
			"urlObter": "https://localhost:3000/Obter/?Tipo_Id=tipo_afastamento_",
			"urlApagar": "https://localhost:3000/Apagar?Tipo_Id=tipo_afastamento_",
			"urlLoadObjetos": "https://localhost:3000/Listar?qualEntidade=tipo_afastamento&pageSize=",
			"urlCount": "https://localhost:3000/CountEntity?qualEntidade=tipo_afastamento",
			"urlIncluir": "https://localhost:3000/Incluir",
			"urlAlterar": "https://localhost:3000/Alterar",
			"nomeEntidade": "tipo_afastamento",
			"nome": "Tipos de Afastamento",
			"camposFormObjeto": ["#codigo", "#nome","#descricao"],
			"labelsFormObjeto": ["Código", "Nome","Descrição"],
			"readOnlyFormObjeto": ["readOnly", "",""],
			"inputFieldFormObjeto": ["<input type=\"text\"", "<input type=\"text\"", "<textarea "],
			"campoObjetoId": "codigo",
			"camposObjeto": ["codigo", "nome","descricao"],
			"camposListagemObjeto": ["nome"],
			"camposFormObjetoOrder": ["1", "2","3"],
			"camposFormClassObjeto": ["form-control", "form-control", "form-control"],
			"tipoCamposObjeto": ["objectid", "text","text"],
			"chooseFormObjeto": ["", "",""]
			
		},
		{
			"id": "ModeloTextoCRUD",
			"tipo": "entity",
			"desligaUrlBase":"true",
			"urlObter": "https://localhost:3000/Obter/?Tipo_Id=modelo_texto_",
			"urlApagar": "https://localhost:3000/Apagar?Tipo_Id=modelo_texto_",
			"urlLoadObjetos": "https://localhost:3000/Listar?qualEntidade=modelo_texto&pageSize=",
			"urlCount": "https://localhost:3000/CountEntity?qualEntidade=modelo_texto",
			"urlIncluir": "https://localhost:3000/Incluir",
			"urlAlterar": "https://localhost:3000/Alterar",
			"nomeEntidade": "modelo_texto",
			"nome": "Modelos de Texto",
			"camposFormObjeto": ["#codigo", "#nome","#texto"],
			"labelsFormObjeto": ["Código", "Nome","Modelo"],
			"readOnlyFormObjeto": ["readOnly", "",""],
			"inputFieldFormObjeto": ["<input type=\"text\"", "<input type=\"text\"", "<textarea "],
			"campoObjetoId": "codigo",
			"camposObjeto": ["codigo", "nome","texto"],
			"camposListagemObjeto": ["nome"],
			"camposFormObjetoOrder": ["1", "2","3"],
			"camposFormClassObjeto": ["form-control", "form-control", "form-control"],
			"tipoCamposObjeto": ["objectid", "text","tinymce"],
			"chooseFormObjeto": ["", "",""]
			
		},
		{
			"id": "RelatorioCRUD",
			"tipo": "entity",
			"desligaUrlBase":"true",
			"urlObter": "https://localhost:3000/Obter/?Tipo_Id=relatorio_",
			"urlApagar": "https://localhost:3000/Apagar?Tipo_Id=relatorio_",
			"urlLoadObjetos": "https://localhost:3000/Listar?qualEntidade=relatorio&pageSize=",
			"urlCount": "https://localhost:3000/CountEntity?qualEntidade=relatorio",
			"urlIncluir": "https://localhost:3000/Incluir",
			"urlAlterar": "https://localhost:3000/Alterar",
			"nomeEntidade": "relatorio",
			"nome": "Relatórios",
			"camposFormObjeto": ["#codigo", "#nome","#parametros"],
			"labelsFormObjeto": ["Código", "Nome","Parâmetros de Informação"],
			"readOnlyFormObjeto": ["readOnly", "",""],
			"inputFieldFormObjeto": ["<input type=\"text\"", "<input type=\"text\"", "<input type=\"text\""],
			"campoObjetoId": "codigo",
			"camposObjeto": ["codigo", "nome","parametros"],
			"camposListagemObjeto": ["nome"],
			"camposFormObjetoOrder": ["1", "2","3"],
			"camposFormClassObjeto": ["form-control", "form-control", "form-control"],
			"tipoCamposObjeto": ["objectid", "text","text"],
			"chooseFormObjeto": ["", "",""]
			
		},
		{
			"id": "ParametroJsonCRUD",
			"tipo": "entity",
			"desligaUrlBase":"true",
			"urlObter": "https://localhost:3000/Obter/?Tipo_Id=parametro_json_",
			"urlApagar": "https://localhost:3000/Apagar?Tipo_Id=parametro_json_",
			"urlLoadObjetos": "https://localhost:3000/Listar?qualEntidade=parametro_json&pageSize=",
			"urlCount": "https://localhost:3000/CountEntity?qualEntidade=parametro_json",
			"urlIncluir": "https://localhost:3000/Incluir",
			"urlAlterar": "https://localhost:3000/Alterar",
			"nomeEntidade": "parametro_json",
			"nome": "Parâmetros JSON",
			"camposFormObjeto": ["#codigo", "#nome","#sql","#parametros_entrada","#parametros_saida","#tipo_parametro"],
			"labelsFormObjeto": ["Código", "Nome","Código SQL", "Variáveis de Entrada", "Variáveis de Saída", "Tipo do Parâmetro JSON"],
			"readOnlyFormObjeto": ["readOnly", "","","","",""],
			"inputFieldFormObjeto": ["<input type=\"text\"", "<input type=\"text\"",  "<textarea ", 
									"<input type=\"text\"", "<input type=\"text\"", "select('simples','lista','tabela')"],
			"campoObjetoId": "codigo",
			"camposObjeto": ["codigo", "nome","sql","parametros_entrada","parametros_saida","tipo_parametro"],
			"camposListagemObjeto": ["nome"],
			"camposFormObjetoOrder": ["1", "2","3","4","5","6"],
			"camposFormClassObjeto": ["form-control", "form-control", "form-control","form-control", "form-control", "form-control"],
			"tipoCamposObjeto": ["objectid", "text","base64", "text","text", "text"],
			"chooseFormObjeto": ["", "","","", "",""]
			
		},
		{
			"id": "SecretariaCRUD",
			"tipo": "entity",
			"desligaUrlBase":"true",
			"urlObter": "https://localhost:3000/Obter/?Tipo_Id=secretaria_",
			"urlApagar": "https://localhost:3000/Apagar?Tipo_Id=secretaria_",
			"urlLoadObjetos": "https://localhost:3000/Listar?qualEntidade=secretaria&pageSize=",
			"urlCount": "https://localhost:3000/CountEntity?qualEntidade=secretaria",
			"urlIncluir": "https://localhost:3000/Incluir",
			"urlAlterar": "https://localhost:3000/Alterar",
			"nomeEntidade": "secretaria",
			"nome": "Secretarias",
			"camposFormObjeto": ["#codigo_regional","#codigo_cidade","#codigo", "#nome","#sigla"],
			"labelsFormObjeto": ["Regional","Cidade","Código", "Nome","Sigla"],
			"readOnlyFormObjeto": ["readOnly","readOnly","readOnly", "",""],
			"inputFieldFormObjeto": ["<input type=\"text\"","<input type=\"text\"","<input type=\"text\"",
										"<input type=\"text\"", "<input type=\"text\""],
			"campoObjetoId": "codigo",
			"camposObjeto": ["codigo_regional","codigo_cidade","codigo", "nome","sigla"],
			"camposListagemObjeto": ["nome","sigla"],
			"camposFormObjetoOrder": ["1", "2","3","4","5"],
			"camposFormClassObjeto": ["form-control","form-control","form-control", "form-control", "form-control"],
			"tipoCamposObjeto": ["objectid","objectid", "objectid","text","text"],
			"chooseFormObjeto": ["RegionalCRUD", "CidadeCRUD","","",""],
			"IdToViewObjeto": ["RegionalCRUD", "CidadeCRUD","","",""]
		},
		{
			"id": "RelatorioParametroJsonCRUD",
			"tipo": "entity",
			"desligaUrlBase":"true",
			"urlObter": "https://localhost:3000/Obter/?Tipo_Id=relatorio_parametro_json_",
			"urlApagar": "https://localhost:3000/Apagar/?Tipo_Id=relatorio_parametro_json_",
			"urlLoadObjetos": "https://localhost:3000/Listar?qualEntidade=relatorio_parametro_json&pageSize=",
			"urlCount": "https://localhost:3000/CountEntity?qualEntidade=relatorio_parametro_json",
			"urlIncluir": "https://localhost:3000/Incluir",
			"urlAlterar": "https://localhost:3000/Alterar",
			"nomeEntidade": "relatorio_parametro_json",
			"nome": "Parâmetros JSON de Relatório",
			"camposFormObjeto": ["#codigo_relatorio", "#codigo_parametro","#de_para"],
			"labelsFormObjeto": ["Código do Relatório", "Código do Parâmetro","De->Para"],
			"readOnlyFormObjeto": ["readOnly", "readOnly",""],
			"inputFieldFormObjeto": ["<input type=\"text\"", "<input type=\"text\"","<input type=\"text\""],
			"campoObjetoId": "codigo_relatorio||codigo_parametro",
			"camposObjeto": ["codigo_relatorio", "codigo_parametro","de_para"],
			"camposListagemObjeto": ["codigo_relatorio", "codigo_parametro","de_para"],
			"camposFormObjetoOrder": ["1", "2","3"],
			"camposFormClassObjeto": ["form-control", "form-control", "form-control"],
			"tipoCamposObjeto": ["objectid", "objectid","text"],
			"chooseFormObjeto": ["RelatorioCRUD", "ParametroJsonCRUD"],
			"IdToViewObjeto": ["RelatorioCRUD", "ParametroJsonCRUD",""]
		},
		{
			"id": "VaraPlantonistaCRUD",
			"tipo": "entity",
			"desligaUrlBase":"true",
			"urlObter": "https://localhost:3000/Obter/?Tipo_Id=vara_plantonista_",
			"urlApagar": "https://localhost:3000/Apagar?Tipo_Id=vara_plantonista_",
			"urlLoadObjetos": "https://localhost:3000/Listar?qualEntidade=vara_plantonista&pageSize=",
			"urlCount": "https://localhost:3000/CountEntity?qualEntidade=vara_plantonista",
			"urlIncluir": "https://localhost:3000/Incluir",
			"urlAlterar": "https://localhost:3000/Alterar",
			"nomeEntidade": "vara_plantonista",
			"nome": "Varas Plantonistas",
			"camposFormObjeto": ["#codigo","#codigo_secretaria","#codigo_tipo_plantao","#inicio","#fim"],
			"labelsFormObjeto": ["Código", "Secretaria","Tipo de Plantão","Início","Fim"],
			"readOnlyFormObjeto": ["readOnly", "readOnly","readOnly","",""],
			"inputFieldFormObjeto": ["<input type=\"text\"", "<input type=\"text\"", "<input type=\"text\"", 
										"<input type=\"text\"", "<input type=\"text\""],
			"campoObjetoId": "codigo",
			"camposObjeto": ["codigo", "codigo_secretaria","codigo_tipo_plantao","inicio","fim"],
			"camposListagemObjeto": ["codigo_secretaria","codigo_tipo_plantao","inicio","fim"],
			"camposFormObjetoOrder": ["1", "2","3","4","5"],
			"camposFormClassObjeto": ["form-control", "form-control", "form-control", "form-control", "form-control"],
			"tipoCamposObjeto": ["objectid", "objectid","objectid","datetime","datetime"],
			"chooseFormObjeto": ["","SecretariaCRUD", "TipoPlantaoCRUD","",""],
			"IdToViewObjeto": ["","SecretariaCRUD", "TipoPlantaoCRUD","",""]
			
		},
		{
			"id": "JuizCRUD",
			"tipo": "entity",
			"desligaUrlBase":"true",
			"urlObter": "https://localhost:3000/Obter/?Tipo_Id=juiz_",
			"urlApagar": "https://localhost:3000/Apagar?Tipo_Id=juiz_",
			"urlLoadObjetos": "https://localhost:3000/Listar?qualEntidade=juiz&pageSize=",
			"urlCount": "https://localhost:3000/CountEntity?qualEntidade=juiz",
			"urlIncluir": "https://localhost:3000/Incluir",
			"urlAlterar": "https://localhost:3000/Alterar",
			"nomeEntidade": "juiz",
			"nome": "Juízes",
			"camposFormObjeto": ["#nome","#rf", "#email","#antiguidade","#cargo","#cod_secretaria"],
			"labelsFormObjeto": ["Nome","RF", "E-mail","Antiguidade","Cargo","Secretaria Lotação"],
			"readOnlyFormObjeto": ["","","", "","","","readOnly"],
			"inputFieldFormObjeto": ["<input type=\"text\"","<input type=\"text\"","<input type=\"text\"",
										"<input type=\"text\"", "<input type=\"text\"", "<input type=\"text\""],
			"campoObjetoId": "rf",
			"camposObjeto": ["nome","rf", "email","antiguidade","cargo","cod_secretaria"],
			"camposListagemObjeto": ["nome"],
			"camposFormObjetoOrder": ["1", "2","3","4","5","6"],
			"camposFormClassObjeto": ["form-control","form-control","form-control", 
										"form-control","form-control", "form-control"],
			"tipoCamposObjeto": ["text", "objectid","text","text","text","objectid"],
			"chooseFormObjeto": ["","","","","","SecretariaCRUD"],
			"IdToViewObjeto": ["","","","","","SecretariaCRUD"]
		},
		{
			"id": "AfastamentoCRUD",
			"tipo": "entity",
			"desligaUrlBase":"true",
			"urlObter": "https://localhost:3000/Obter/?Tipo_Id=afastamento_",
			"urlApagar": "https://localhost:3000/Apagar?Tipo_Id=afastamento_",
			"urlLoadObjetos": "https://localhost:3000/Listar?qualEntidade=afastamento&pageSize=",
			"urlCount": "https://localhost:3000/CountEntity?qualEntidade=afastamento",
			"urlIncluir": "https://localhost:3000/Incluir",
			"urlAlterar": "https://localhost:3000/Alterar",
			"nomeEntidade": "afastamento",
			"nome": "Afastamentos",
			"camposFormObjeto": ["#codigo","#rf_juiz","#codigo_tipo_afastamento", "#inicio","#fim"],
			"labelsFormObjeto": ["Código","Juiz","Tipo de Afastamento", "Início","Fim"],
			"readOnlyFormObjeto": ["readOnly","readOnly","readOnly", "",""],
			"inputFieldFormObjeto": ["<input type=\"text\"","<input type=\"text\"","<input type=\"text\"",
										"<input type=\"text\"", "<input type=\"text\""],
			"campoObjetoId": "codigo",
			"camposObjeto": ["codigo","rf_juiz","codigo_tipo_afastamento", "inicio","fim"],
			"camposListagemObjeto": ["rf_juiz","codigo_tipo_afastamento","inicio","fim"],
			"camposFormObjetoOrder": ["1", "2","3","4","5"],
			"camposFormClassObjeto": ["form-control","form-control","form-control","form-control","form-control"],
			"tipoCamposObjeto": ["objectid", "objectid","objectid","date","date"],
			"chooseFormObjeto": ["","JuizCRUD","TipoAfastamentoCRUD","",""],
			"IdToViewObjeto": ["","JuizCRUD","TipoAfastamentoCRUD","",""]
		},
		{
			"id": "EscalaPlantaoCRUD",
			"tipo": "entity",
			"desligaUrlBase":"true",
			"urlObter": "https://localhost:3000/Obter/?Tipo_Id=escala_plantao_",
			"urlApagar": "https://localhost:3000/Apagar?Tipo_Id=escala_plantao_",
			"urlLoadObjetos": "https://localhost:3000/Listar?qualEntidade=escala_plantao&pageSize=",
			"urlCount": "https://localhost:3000/CountEntity?qualEntidade=escala_plantao",
			"urlIncluir": "https://localhost:3000/Incluir",
			"urlAlterar": "https://localhost:3000/Alterar",
			"nomeEntidade": "escala_plantao",
			"nome": "Escalas de Plantão",
			"camposFormObjeto": ["#codigo","#rf_juiz_ativo_para_escolha","#nome", "#codigo_tipo_plantao","#inicio","#fim","#fase"],
			"labelsFormObjeto": ["Código","Juiz Ativo para Escolha","Nome da Escala de Plantão","Tipo de Plantão",
									 "Início","Fim","Fase"],
			"readOnlyFormObjeto": ["readOnly","readOnly","", "readOnly","","","readOnly"],
			"Defaults": ["","","", "","","","criada"],
			"inputFieldFormObjeto": ["<input type=\"text\"","<input type=\"text\"","<input type=\"text\"","<input type=\"text\"",
										"<input type=\"text\"", "<input type=\"text\"", "<input type=\"text\""],
			"campoObjetoId": "codigo",
			"camposObjeto": ["codigo","rf_juiz_ativo_para_escolha","nome","codigo_tipo_plantao", "inicio","fim","fase"],
			"camposListagemObjeto": ["nome","codigo_tipo_plantao","inicio","fim","fase"],
			"camposFormObjetoOrder": ["1", "2","3","4","5","6","7"],
			"camposFormClassObjeto": ["form-control","form-control","form-control","form-control"
										,"form-control","form-control","form-control"],
			"tipoCamposObjeto": ["objectid", "objectid","text","objectid","date","date","text"],
			"chooseFormObjeto": ["","JuizCRUD","","TipoPlantaoCRUD","","",""],
			"IdToViewObjeto": ["","JuizCRUD","","TipoPlantaoCRUD","","",""],			
			"minicrud": [
				{ "rotuloInterface": "Regionais","entity": "EscalaPlantaoRegionalCRUD",
					"DeForm": "#codigo",
					"De": "codigo_escala_plantao",
				    "Para": "codigo_escala_plantao"
				}				
			]
		},
		{
			"id": "EscalaPlantaoRegionalCRUD",
			"tipo": "entity",
			"desligaUrlBase":"true",
			"urlObter": "https://localhost:3000/Obter/?Tipo_Id=escala_plantao_regional_",
			"urlApagar": "https://localhost:3000/Apagar/?Tipo_Id=escala_plantao_regional_",
			"urlLoadObjetos": "https://localhost:3000/Listar?qualEntidade=escala_plantao_regional&pageSize=",
			"urlCount": "https://localhost:3000/CountEntity?qualEntidade=escala_plantao_regional",
			"urlIncluir": "https://localhost:3000/Incluir",
			"urlAlterar": "https://localhost:3000/Alterar",
			"nomeEntidade": "escala_plantao_regional",
			"nome": "Regionais da Escala",
			"camposFormObjeto": ["#codigo_escala_plantao", "#codigo_regional"],
			"labelsFormObjeto": ["Escala de Plantão", "Regional"],
			"readOnlyFormObjeto": ["readOnly", "readOnly"],
			"inputFieldFormObjeto": ["<input type=\"text\"", "<input type=\"text\""],
			"campoObjetoId": "codigo_escala_plantao||codigo_regional",
			"camposObjeto": ["codigo_escala_plantao", "codigo_regional"],
			"camposListagemObjeto": ["codigo_escala_plantao", "codigo_regional"],
			"camposFormObjetoOrder": ["1", "2"],
			"camposFormClassObjeto": ["form-control", "form-control"],
			"tipoCamposObjeto": ["objectid", "objectid"],
			"chooseFormObjeto": ["EscalaPlantaoCRUD", "RegionalCRUD"],
			"IdToViewObjeto": ["", "RegionalCRUD"]
		},
		{
			"id": "RegionalCRUD",
			"tipo": "entity",
			"desligaUrlBase":"true",
			"urlObter": "https://localhost:3000/Obter/?Tipo_Id=regional_",
			"urlApagar": "https://localhost:3000/Apagar?Tipo_Id=regional_",
			"urlLoadObjetos": "https://localhost:3000/Listar?qualEntidade=regional&pageSize=",
			"urlCount": "https://localhost:3000/CountEntity?qualEntidade=regional",
			"urlIncluir": "https://localhost:3000/Incluir",
			"urlAlterar": "https://localhost:3000/Alterar",
			"nomeEntidade": "regional",
			"nome": "Regionais",
			"camposFormObjeto": ["#codigo", "#nome"],
			"labelsFormObjeto": ["Código", "Nome"],
			"readOnlyFormObjeto": ["readOnly", ""],
			"inputFieldFormObjeto": ["<input type=\"text\"", "<input type=\"text\""],
			"campoObjetoId": "codigo",
			"camposObjeto": ["codigo", "nome"],
			"camposListagemObjeto": ["nome"],
			"camposFormObjetoOrder": ["1", "2"],
			"camposFormClassObjeto": ["form-control", "form-control"],
			"tipoCamposObjeto": ["objectid", "text"],
			"chooseFormObjeto": ["", ""]
		}											
	]
}